onad/__init__.py
onad/base/__init__.py
onad/base/architecture.py
onad/base/exceptions.py
onad/base/model.py
onad/base/pipeline.py
onad/base/similarity.py
onad/base/transformer.py
onad/model/__init__.py
onad/model/null.py
onad/model/random.py
onad/model/threshold.py
onad/model/deep/__init__.py
onad/model/deep/autoencoder.py
onad/model/distance/__init__.py
onad/model/distance/knn.py
onad/model/iforest/__init__.py
onad/model/iforest/asd.py
onad/model/iforest/mondrian.py
onad/model/iforest/online.py
onad/model/iforest/rand_hist.py
onad/model/stat/__init__.py
onad/model/stat/multi.py
onad/model/stat/uni.py
onad/model/svm/__init__.py
onad/model/svm/adaptive.py
onad/model/svm/gadget.py
onad/model/svm/todo.txt
onad/stream/__init__.py
onad/stream/streamer.py
onad/stream/dataset/__init__.py
onad/stream/dataset/loader.py
onad/stream/dataset/registry.py
onad/stream/dataset/streamers.py
onad/transform/__init__.py
onad/transform/preprocessing/__init__.py
onad/transform/preprocessing/scaler.py
onad/transform/projection/__init__.py
onad/transform/projection/incremental_pca.py
onad/transform/projection/random_projection.py
onad/utils/__init__.py
onad/utils/deep/__init__.py
onad/utils/deep/architecture.py
onad/utils/deep/loss_func.py
onad/utils/similar/__init__.py
onad/utils/similar/faiss_engine.py
onad-0.3.0.dist-info/METADATA
onad-0.3.0.dist-info/WHEEL
onad-0.3.0.dist-info/licenses/LICENSE
onad-0.3.0.dist-info/RECORD
