Metadata-Version: 2.4
Name: onad
Version: 0.3.0
Summary: Online Anomaly Detection Toolkit
Project-URL: Homepage, https://github.com/OliverHennhoefer/onad
Project-URL: Bugs, https://github.com/OliverHennhoefer/onad/issues
Author: Pascal Heinzelmann, Marius Höll, Marco Catoir
Author-email: Oliver Hennhoefer <oliver.hennhoefer@mail.de>
Maintainer-email: Oliver Hennhoefer <oliver.hennhoefer@mail.de>
License: MIT License
License-File: LICENSE
Classifier: License :: OSI Approved :: BSD License
Classifier: Operating System :: OS Independent
Classifier: Programming Language :: Python :: 3.10
Requires-Python: >=3.10
Requires-Dist: faiss-cpu>=1.10.0
Requires-Dist: numpy>=2.2.3
Requires-Dist: scipy>=1.15.2
Requires-Dist: tqdm>=4.67.1
Provides-Extra: all
Requires-Dist: mkdocs; extra == 'all'
Requires-Dist: mkdocs-material[imaging]; extra == 'all'
Requires-Dist: mkdocstrings[python]; extra == 'all'
Requires-Dist: mypy<2.0.0,>=1.13.0; extra == 'all'
Requires-Dist: pre-commit<5.0.0,>=4.0.0; extra == 'all'
Requires-Dist: pytest-cov<7.0.0,>=6.0.0; extra == 'all'
Requires-Dist: pytest<9.0.0,>=8.0.0; extra == 'all'
Requires-Dist: river<1.0.0,>=0.22.0; extra == 'all'
Requires-Dist: ruff<1.0.0,>=0.8.0; extra == 'all'
Requires-Dist: scikit-learn<2.0.0,>=1.6.1; extra == 'all'
Requires-Dist: torch<3.0.0,>=2.6.0; extra == 'all'
Provides-Extra: benchmark
Requires-Dist: river<1.0.0,>=0.22.0; extra == 'benchmark'
Provides-Extra: dev
Requires-Dist: mypy<2.0.0,>=1.13.0; extra == 'dev'
Requires-Dist: pre-commit<5.0.0,>=4.0.0; extra == 'dev'
Requires-Dist: pytest-cov<7.0.0,>=6.0.0; extra == 'dev'
Requires-Dist: pytest<9.0.0,>=8.0.0; extra == 'dev'
Requires-Dist: ruff<1.0.0,>=0.8.0; extra == 'dev'
Provides-Extra: dl
Requires-Dist: torch<3.0.0,>=2.6.0; extra == 'dl'
Provides-Extra: docs
Requires-Dist: mkdocs; extra == 'docs'
Requires-Dist: mkdocs-material[imaging]; extra == 'docs'
Requires-Dist: mkdocstrings[python]; extra == 'docs'
Provides-Extra: eval
Requires-Dist: scikit-learn<2.0.0,>=1.6.1; extra == 'eval'
